aws_recommendation_a16/__init__.py
aws_recommendation_a16/cloudwatch.py
aws_recommendation_a16/cost_estimations.py
aws_recommendation_a16/dynamodb.py
aws_recommendation_a16/ebs.py
aws_recommendation_a16/ec2.py
aws_recommendation_a16/elb.py
aws_recommendation_a16/kms.py
aws_recommendation_a16/rds.py
aws_recommendation_a16/recommendation.py
aws_recommendation_a16/redshift.py
aws_recommendation_a16/s3.py
aws_recommendation_a16/truted_advisor.py
aws_recommendation_a16/utils.py
aws_recommendation_a16-0.1.0.dist-info/LICENCE
aws_recommendation_a16-0.1.0.dist-info/METADATA
aws_recommendation_a16-0.1.0.dist-info/WHEEL
aws_recommendation_a16-0.1.0.dist-info/top_level.txt
aws_recommendation_a16-0.1.0.dist-info/RECORD
